manim_ml/__init__.py
manim_ml/scene.py
manim_ml/neural_network/__init__.py
manim_ml/neural_network/neural_network.py
manim_ml/neural_network/activation_functions/__init__.py
manim_ml/neural_network/activation_functions/activation_function.py
manim_ml/neural_network/activation_functions/relu.py
manim_ml/neural_network/activation_functions/sigmoid.py
manim_ml/neural_network/animations/__init__.py
manim_ml/neural_network/animations/dropout.py
manim_ml/neural_network/animations/neural_network_transformations.py
manim_ml/neural_network/architectures/__init__.py
manim_ml/neural_network/architectures/feed_forward.py
manim_ml/neural_network/architectures/variational_autoencoder.py
manim_ml/neural_network/layers/__init__.py
manim_ml/neural_network/layers/convolutional_2d.py
manim_ml/neural_network/layers/convolutional_2d_to_convolutional_2d.py
manim_ml/neural_network/layers/convolutional_2d_to_feed_forward.py
manim_ml/neural_network/layers/convolutional_2d_to_max_pooling_2d.py
manim_ml/neural_network/layers/embedding.py
manim_ml/neural_network/layers/embedding_to_feed_forward.py
manim_ml/neural_network/layers/feed_forward.py
manim_ml/neural_network/layers/feed_forward_to_embedding.py
manim_ml/neural_network/layers/feed_forward_to_feed_forward.py
manim_ml/neural_network/layers/feed_forward_to_image.py
manim_ml/neural_network/layers/feed_forward_to_math_operation.py
manim_ml/neural_network/layers/feed_forward_to_vector.py
manim_ml/neural_network/layers/image.py
manim_ml/neural_network/layers/image_to_convolutional_2d.py
manim_ml/neural_network/layers/image_to_feed_forward.py
manim_ml/neural_network/layers/math_operation_layer.py
manim_ml/neural_network/layers/max_pooling_2d.py
manim_ml/neural_network/layers/max_pooling_2d_to_convolutional_2d.py
manim_ml/neural_network/layers/max_pooling_2d_to_feed_forward.py
manim_ml/neural_network/layers/paired_query.py
manim_ml/neural_network/layers/paired_query_to_feed_forward.py
manim_ml/neural_network/layers/parent_layers.py
manim_ml-0.0.24.dist-info/LICENSE.md
manim_ml-0.0.24.dist-info/METADATA
manim_ml-0.0.24.dist-info/WHEEL
manim_ml-0.0.24.dist-info/top_level.txt
manim_ml-0.0.24.dist-info/RECORD
