Metadata-Version: 2.1
Name: manim_ml
Version: 0.0.24
Summary: Machine Learning Animations in python using Manim.
Home-page: https://github.com/helblazer811/ManimMachineLearning
Author: Alec Helbling
Project-URL: Bug Tracker, https://github.com/helblazer811/ManimMachineLearning/issues
Classifier: Programming Language :: Python :: 3
Classifier: License :: OSI Approved :: MIT License
Classifier: Operating System :: OS Independent
Requires-Python: >=3.6
License-File: LICENSE.md
